README.md
setup.py
K_Format.egg-info/PKG-INFO
K_Format.egg-info/SOURCES.txt
K_Format.egg-info/dependency_links.txt
K_Format.egg-info/top_level.txt
kformat/__init__.py
kformat/kclass.py
kformat/kproperty.py