Metadata-Version: 1.2
Name: K-Format
Version: 0.3.0
Summary: Python Library for dealing with KCB K-Format
Home-page: https://github.com/Rainist/K-Format
Author: Sunghyun Hwang
Author-email: me@sunghyunzz.com
Maintainer: Rainist
Maintainer-email: engineering@rainist.com
License: MIT
Platform: UNKNOWN
Classifier: Development Status :: 3 - Alpha
Classifier: Operating System :: OS Independent
Classifier: License :: OSI Approved :: MIT License
Classifier: Programming Language :: Python :: 3.7
Requires-Python: >=3.7
